[
  {
    "gameId": "18446827",
    "date": "2025-10-22",
    "opponent": "CHI",
    "team": "DET",
    "season": "2025-26",
    "buckets": {
      "PG": 31,
      "SG": 29,
      "SF": 0,
      "PF": 25,
      "C": 30
    },
    "players": [
      {
        "playerId": 3547247,
        "name": "Isaac Okoro",
        "bucket": "SF",
        "isStarter": false,
        "pts": 0,
        "reb": 5,
        "ast": 4,
        "fg3m": 0,
        "fg3a": 0,
        "fga": 2,
        "fgm": 0,
        "stl": 0,
        "blk": 0
      },
      {
        "playerId": 1028025177,
        "name": "Matas Buzelis",
        "bucket": "PF",
        "isStarter": false,
        "pts": 21,
        "reb": 6,
        "ast": 1,
        "fg3m": 0,
        "fg3a": 3,
        "fga": 12,
        "fgm": 7,
        "stl": 0,
        "blk": 3
      },
      {
        "playerId": 460,
        "name": "Nikola Vucevic",
        "bucket": "C",
        "isStarter": false,
        "pts": 28,
        "reb": 14,
        "ast": 2,
        "fg3m": 4,
        "fg3a": 6,
        "fga": 18,
        "fgm": 11,
        "stl": 1,
        "blk": 0
      },
      {
        "playerId": 3547274,
        "name": "Tre Jones",
        "bucket": "PG",
        "isStarter": false,
        "pts": 12,
        "reb": 1,
        "ast": 8,
        "fg3m": 1,
        "fg3a": 1,
        "fga": 8,
        "fgm": 5,
        "stl": 3,
        "blk": 0
      },
      {
        "playerId": 17896065,
        "name": "Josh Giddey",
        "bucket": "PG",
        "isStarter": false,
        "pts": 19,
        "reb": 5,
        "ast": 11,
        "fg3m": 1,
        "fg3a": 2,
        "fga": 12,
        "fgm": 5,
        "stl": 0,
        "blk": 1
      },
      {
        "playerId": 87,
        "name": "Jevon Carter",
        "bucket": "PG",
        "isStarter": false,
        "pts": 0,
        "reb": 0,
        "ast": 0,
        "fg3m": 0,
        "fg3a": 0,
        "fga": 0,
        "fgm": 0,
        "stl": 0,
        "blk": 0
      },
      {
        "playerId": 17895983,
        "name": "Ayo Dosunmu",
        "bucket": "SG",
        "isStarter": false,
        "pts": 14,
        "reb": 5,
        "ast": 2,
        "fg3m": 2,
        "fg3a": 5,
        "fga": 14,
        "fgm": 6,
        "stl": 0,
        "blk": 0
      },
      {
        "playerId": 1057272081,
        "name": "Noa Essengue",
        "bucket": "PF",
        "isStarter": false,
        "pts": 0,
        "reb": 0,
        "ast": 0,
        "fg3m": 0,
        "fg3a": 0,
        "fga": 0,
        "fgm": 0,
        "stl": 0,
        "blk": 0
      },
      {
        "playerId": 221,
        "name": "Kevin Huerter",
        "bucket": "SG",
        "isStarter": false,
        "pts": 15,
        "reb": 5,
        "ast": 0,
        "fg3m": 2,
        "fg3a": 6,
        "fga": 11,
        "fgm": 4,
        "stl": 1,
        "blk": 2
      },
      {
        "playerId": 56677857,
        "name": "Julian Phillips",
        "bucket": "SF",
        "isStarter": false,
        "pts": 0,
        "reb": 0,
        "ast": 0,
        "fg3m": 0,
        "fg3a": 0,
        "fga": 0,
        "fgm": 0,
        "stl": 0,
        "blk": 0
      },
      {
        "playerId": 3547264,
        "name": "Jalen Smith",
        "bucket": "C",
        "isStarter": false,
        "pts": 2,
        "reb": 5,
        "ast": 1,
        "fg3m": 0,
        "fg3a": 5,
        "fga": 7,
        "fgm": 0,
        "stl": 0,
        "blk": 0
      },
      {
        "playerId": 1057395493,
        "name": "Lachlan Olbrich",
        "bucket": "C",
        "isStarter": false,
        "pts": 0,
        "reb": 0,
        "ast": 0,
        "fg3m": 0,
        "fg3a": 0,
        "fga": 0,
        "fgm": 0,
        "stl": 0,
        "blk": 0
      },
      {
        "playerId": 666956,
        "name": "Coby White",
        "bucket": "SF",
        "isStarter": false,
        "pts": 0,
        "reb": 0,
        "ast": 0,
        "fg3m": 0,
        "fg3a": 0,
        "fga": 0,
        "fgm": 0,
        "stl": 0,
        "blk": 0
      },
      {
        "playerId": 38017719,
        "name": "Dalen Terry",
        "bucket": "PF",
        "isStarter": false,
        "pts": 0,
        "reb": 0,
        "ast": 0,
        "fg3m": 0,
        "fg3a": 0,
        "fga": 1,
        "fgm": 0,
        "stl": 0,
        "blk": 0
      },
      {
        "playerId": 3547248,
        "name": "Patrick Williams",
        "bucket": "PF",
        "isStarter": false,
        "pts": 4,
        "reb": 4,
        "ast": 0,
        "fg3m": 1,
        "fg3a": 2,
        "fga": 2,
        "fgm": 1,
        "stl": 1,
        "blk": 2
      },
      {
        "playerId": 102,
        "name": "Zach Collins",
        "bucket": "SF",
        "isStarter": false,
        "pts": 0,
        "reb": 0,
        "ast": 0,
        "fg3m": 0,
        "fg3a": 0,
        "fga": 0,
        "fgm": 0,
        "stl": 0,
        "blk": 0
      },
      {
        "playerId": 1028254340,
        "name": "Trentyn Flowers",
        "bucket": "SG",
        "isStarter": false,
        "pts": 0,
        "reb": 0,
        "ast": 0,
        "fg3m": 0,
        "fg3a": 0,
        "fga": 0,
        "fgm": 0,
        "stl": 0,
        "blk": 0
      },
      {
        "playerId": 1028245974,
        "name": "Emanuel Miller",
        "bucket": "SF",
        "isStarter": false,
        "pts": 0,
        "reb": 0,
        "ast": 0,
        "fg3m": 0,
        "fg3a": 0,
        "fga": 0,
        "fgm": 0,
        "stl": 0,
        "blk": 0
      }
    ],
    "source": "bdl+nba"
  },
  {
    "gameId": "18446840",
    "date": "2025-10-24",
    "opponent": "HOU",
    "team": "DET",
    "season": "2025-26",
    "buckets": {
      "PG": 19,
      "SG": 47,
      "SF": 15,
      "PF": 17,
      "C": 13
    },
    "players": [
      {
        "playerId": 38017684,
        "name": "Jabari Smith Jr.",
        "bucket": "SF",
        "isStarter": false,
        "pts": 11,
        "reb": 6,
        "ast": 2,
        "fg3m": 3,
        "fg3a": 9,
        "fga": 14,
        "fgm": 3,
        "stl": 1,
        "blk": 1
      },
      {
        "playerId": 17896062,
        "name": "Alperen Sengun",
        "bucket": "PF",
        "isStarter": false,
        "pts": 17,
        "reb": 7,
        "ast": 7,
        "fg3m": 0,
        "fg3a": 2,
        "fga": 18,
        "fgm": 5,
        "stl": 3,
        "blk": 0
      },
      {
        "playerId": 3,
        "name": "Steven Adams",
        "bucket": "C",
        "isStarter": false,
        "pts": 11,
        "reb": 10,
        "ast": 0,
        "fg3m": 0,
        "fg3a": 0,
        "fga": 4,
        "fgm": 4,
        "stl": 3,
        "blk": 0
      },
      {
        "playerId": 140,
        "name": "Kevin Durant",
        "bucket": "SG",
        "isStarter": false,
        "pts": 37,
        "reb": 3,
        "ast": 1,
        "fg3m": 3,
        "fg3a": 3,
        "fga": 18,
        "fgm": 9,
        "stl": 3,
        "blk": 1
      },
      {
        "playerId": 56677825,
        "name": "Amen Thompson",
        "bucket": "PG",
        "isStarter": false,
        "pts": 10,
        "reb": 4,
        "ast": 1,
        "fg3m": 0,
        "fg3a": 1,
        "fga": 8,
        "fgm": 2,
        "stl": 0,
        "blk": 0
      },
      {
        "playerId": 83,
        "name": "Clint Capela",
        "bucket": "C",
        "isStarter": false,
        "pts": 2,
        "reb": 4,
        "ast": 0,
        "fg3m": 0,
        "fg3a": 0,
        "fga": 1,
        "fgm": 1,
        "stl": 0,
        "blk": 0
      },
      {
        "playerId": 38017707,
        "name": "JD Davison",
        "bucket": "PG",
        "isStarter": false,
        "pts": 0,
        "reb": 0,
        "ast": 0,
        "fg3m": 0,
        "fg3a": 0,
        "fga": 0,
        "fgm": 0,
        "stl": 0,
        "blk": 0
      },
      {
        "playerId": 38017695,
        "name": "Tari Eason",
        "bucket": "SF",
        "isStarter": false,
        "pts": 4,
        "reb": 5,
        "ast": 2,
        "fg3m": 0,
        "fg3a": 1,
        "fga": 5,
        "fgm": 2,
        "stl": 1,
        "blk": 0
      },
      {
        "playerId": 188,
        "name": "Jeff Green",
        "bucket": "SF",
        "isStarter": false,
        "pts": 0,
        "reb": 0,
        "ast": 0,
        "fg3m": 0,
        "fg3a": 0,
        "fga": 0,
        "fgm": 0,
        "stl": 0,
        "blk": 0
      },
      {
        "playerId": 213,
        "name": "Aaron Holiday",
        "bucket": "PG",
        "isStarter": false,
        "pts": 0,
        "reb": 0,
        "ast": 0,
        "fg3m": 0,
        "fg3a": 0,
        "fga": 0,
        "fgm": 0,
        "stl": 0,
        "blk": 0
      },
      {
        "playerId": 356,
        "name": "Josh Okogie",
        "bucket": "SG",
        "isStarter": false,
        "pts": 10,
        "reb": 4,
        "ast": 1,
        "fg3m": 1,
        "fg3a": 2,
        "fga": 4,
        "fgm": 3,
        "stl": 0,
        "blk": 0
      },
      {
        "playerId": 1028028519,
        "name": "Reed Sheppard",
        "bucket": "PG",
        "isStarter": false,
        "pts": 9,
        "reb": 2,
        "ast": 1,
        "fg3m": 3,
        "fg3a": 4,
        "fga": 11,
        "fgm": 3,
        "stl": 3,
        "blk": 0
      },
      {
        "playerId": 3547301,
        "name": "Jae'Sean Tate",
        "bucket": "SF",
        "isStarter": false,
        "pts": 0,
        "reb": 0,
        "ast": 0,
        "fg3m": 0,
        "fg3a": 0,
        "fga": 0,
        "fgm": 0,
        "stl": 0,
        "blk": 0
      },
      {
        "playerId": 1028203948,
        "name": "Isaiah Crawford",
        "bucket": "SF",
        "isStarter": false,
        "pts": 0,
        "reb": 0,
        "ast": 0,
        "fg3m": 0,
        "fg3a": 0,
        "fga": 0,
        "fgm": 0,
        "stl": 0,
        "blk": 0
      },
      {
        "playerId": 158,
        "name": "Dorian Finney-Smith",
        "bucket": "SF",
        "isStarter": false,
        "pts": 0,
        "reb": 0,
        "ast": 0,
        "fg3m": 0,
        "fg3a": 0,
        "fga": 0,
        "fgm": 0,
        "stl": 0,
        "blk": 0
      },
      {
        "playerId": 38017607,
        "name": "Kevon Harris",
        "bucket": "SF",
        "isStarter": false,
        "pts": 0,
        "reb": 0,
        "ast": 0,
        "fg3m": 0,
        "fg3a": 0,
        "fga": 0,
        "fgm": 0,
        "stl": 0,
        "blk": 0
      },
      {
        "playerId": 458,
        "name": "Fred VanVleet",
        "bucket": "SF",
        "isStarter": false,
        "pts": 0,
        "reb": 0,
        "ast": 0,
        "fg3m": 0,
        "fg3a": 0,
        "fga": 0,
        "fgm": 0,
        "stl": 0,
        "blk": 0
      }
    ],
    "source": "bdl+nba"
  },
  {
    "gameId": "18446853",
    "date": "2025-10-26",
    "opponent": "BOS",
    "team": "DET",
    "season": "2025-26",
    "buckets": {
      "PG": 27,
      "SG": 21,
      "SF": 18,
      "PF": 41,
      "C": 6
    },
    "players": [
      {
        "playerId": 38017715,
        "name": "Josh Minott",
        "bucket": "SF",
        "isStarter": false,
        "pts": 10,
        "reb": 1,
        "ast": 1,
        "fg3m": 1,
        "fg3a": 3,
        "fga": 5,
        "fgm": 3,
        "stl": 3,
        "blk": 0
      },
      {
        "playerId": 1028028434,
        "name": "Baylor Scheierman",
        "bucket": "SG",
        "isStarter": false,
        "pts": 0,
        "reb": 2,
        "ast": 0,
        "fg3m": 0,
        "fg3a": 0,
        "fga": 0,
        "fgm": 0,
        "stl": 0,
        "blk": 0
      },
      {
        "playerId": 1057396191,
        "name": "Max Shulga",
        "bucket": "PG",
        "isStarter": false,
        "pts": 0,
        "reb": 0,
        "ast": 0,
        "fg3m": 0,
        "fg3a": 0,
        "fga": 0,
        "fgm": 0,
        "stl": 0,
        "blk": 0
      },
      {
        "playerId": 419,
        "name": "Anfernee Simons",
        "bucket": "PG",
        "isStarter": false,
        "pts": 12,
        "reb": 1,
        "ast": 0,
        "fg3m": 2,
        "fg3a": 7,
        "fga": 13,
        "fgm": 5,
        "stl": 0,
        "blk": 0
      },
      {
        "playerId": 434,
        "name": "Jayson Tatum",
        "bucket": "SF",
        "isStarter": false,
        "pts": 0,
        "reb": 0,
        "ast": 0,
        "fg3m": 0,
        "fg3a": 0,
        "fga": 0,
        "fgm": 0,
        "stl": 0,
        "blk": 0
      },
      {
        "playerId": 3547285,
        "name": "Xavier Tillman",
        "bucket": "C",
        "isStarter": false,
        "pts": 0,
        "reb": 0,
        "ast": 0,
        "fg3m": 0,
        "fg3a": 0,
        "fga": 0,
        "fgm": 0,
        "stl": 0,
        "blk": 0
      },
      {
        "playerId": 56677864,
        "name": "Jordan Walsh",
        "bucket": "SF",
        "isStarter": false,
        "pts": 0,
        "reb": 0,
        "ast": 0,
        "fg3m": 0,
        "fg3a": 0,
        "fga": 0,
        "fgm": 0,
        "stl": 0,
        "blk": 0
      },
      {
        "playerId": 1057396966,
        "name": "Amari Williams",
        "bucket": "C",
        "isStarter": false,
        "pts": 0,
        "reb": 0,
        "ast": 0,
        "fg3m": 0,
        "fg3a": 0,
        "fga": 0,
        "fgm": 0,
        "stl": 0,
        "blk": 0
      },
      {
        "playerId": 1057277425,
        "name": "Hugo González",
        "bucket": "SF",
        "isStarter": false,
        "pts": 0,
        "reb": 1,
        "ast": 0,
        "fg3m": 0,
        "fg3a": 0,
        "fga": 2,
        "fgm": 0,
        "stl": 2,
        "blk": 1
      },
      {
        "playerId": 70,
        "name": "Jaylen Brown",
        "bucket": "PF",
        "isStarter": false,
        "pts": 41,
        "reb": 6,
        "ast": 4,
        "fg3m": 5,
        "fg3a": 9,
        "fga": 25,
        "fgm": 12,
        "stl": 0,
        "blk": 0
      },
      {
        "playerId": 17553967,
        "name": "Neemias Queta",
        "bucket": "C",
        "isStarter": false,
        "pts": 4,
        "reb": 6,
        "ast": 3,
        "fg3m": 0,
        "fg3a": 0,
        "fga": 4,
        "fgm": 2,
        "stl": 2,
        "blk": 3
      },
      {
        "playerId": 473,
        "name": "Derrick White",
        "bucket": "PG",
        "isStarter": false,
        "pts": 15,
        "reb": 4,
        "ast": 3,
        "fg3m": 3,
        "fg3a": 11,
        "fga": 18,
        "fgm": 6,
        "stl": 4,
        "blk": 2
      },
      {
        "playerId": 3547276,
        "name": "Payton Pritchard",
        "bucket": "SG",
        "isStarter": false,
        "pts": 21,
        "reb": 10,
        "ast": 4,
        "fg3m": 2,
        "fg3a": 8,
        "fga": 16,
        "fgm": 8,
        "stl": 0,
        "blk": 0
      },
      {
        "playerId": 58,
        "name": "Chris Boucher",
        "bucket": "PF",
        "isStarter": false,
        "pts": 0,
        "reb": 1,
        "ast": 1,
        "fg3m": 0,
        "fg3a": 1,
        "fga": 2,
        "fgm": 0,
        "stl": 0,
        "blk": 1
      },
      {
        "playerId": 17896056,
        "name": "Luka Garza",
        "bucket": "C",
        "isStarter": false,
        "pts": 2,
        "reb": 2,
        "ast": 1,
        "fg3m": 0,
        "fg3a": 1,
        "fga": 2,
        "fgm": 1,
        "stl": 0,
        "blk": 0
      },
      {
        "playerId": 38017717,
        "name": "Ron Harper Jr.",
        "bucket": "SF",
        "isStarter": false,
        "pts": 0,
        "reb": 0,
        "ast": 0,
        "fg3m": 0,
        "fg3a": 0,
        "fga": 0,
        "fgm": 0,
        "stl": 0,
        "blk": 0
      },
      {
        "playerId": 17896060,
        "name": "Sam Hauser",
        "bucket": "SF",
        "isStarter": false,
        "pts": 8,
        "reb": 4,
        "ast": 0,
        "fg3m": 2,
        "fg3a": 5,
        "fga": 7,
        "fgm": 3,
        "stl": 0,
        "blk": 0
      }
    ],
    "source": "bdl+nba"
  },
  {
    "gameId": "18446861",
    "date": "2025-10-27",
    "opponent": "CLE",
    "team": "DET",
    "season": "2025-26",
    "buckets": {
      "PG": 7,
      "SG": 46,
      "SF": 23,
      "PF": 15,
      "C": 25
    },
    "players": [
      {
        "playerId": 666656,
        "name": "De'Andre Hunter",
        "bucket": "SF",
        "isStarter": false,
        "pts": 13,
        "reb": 5,
        "ast": 6,
        "fg3m": 2,
        "stl": 1,
        "blk": 0,
        "min": "24"
      },
      {
        "playerId": 17896076,
        "name": "Evan Mobley",
        "bucket": "PF",
        "isStarter": true,
        "pts": 15,
        "reb": 11,
        "ast": 5,
        "fg3m": 1,
        "stl": 1,
        "blk": 3,
        "min": "30"
      },
      {
        "playerId": 9,
        "name": "Jarrett Allen",
        "bucket": "C",
        "isStarter": true,
        "pts": 20,
        "reb": 7,
        "ast": 2,
        "fg3m": 0,
        "stl": 1,
        "blk": 0,
        "min": "25"
      },
      {
        "playerId": 3547299,
        "name": "Sam Merrill",
        "bucket": "SG",
        "isStarter": false,
        "pts": 11,
        "reb": 1,
        "ast": 1,
        "fg3m": 3,
        "stl": 2,
        "blk": 0,
        "min": "18"
      },
      {
        "playerId": 322,
        "name": "Donovan Mitchell",
        "bucket": "SG",
        "isStarter": true,
        "pts": 35,
        "reb": 1,
        "ast": 2,
        "fg3m": 2,
        "stl": 0,
        "blk": 0,
        "min": "29"
      },
      {
        "playerId": 74,
        "name": "Thomas Bryant",
        "bucket": "C",
        "isStarter": false,
        "pts": 2,
        "reb": 1,
        "ast": 0,
        "fg3m": 0,
        "stl": 0,
        "blk": 0,
        "min": "07"
      },
      {
        "playerId": 340,
        "name": "Larry Nance Jr.",
        "bucket": "C",
        "isStarter": false,
        "pts": 3,
        "reb": 4,
        "ast": 2,
        "fg3m": 1,
        "stl": 0,
        "blk": 1,
        "min": "18"
      },
      {
        "playerId": 56677872,
        "name": "Craig Porter",
        "bucket": "PG",
        "isStarter": false,
        "pts": 4,
        "reb": 7,
        "ast": 3,
        "fg3m": 0,
        "stl": 3,
        "blk": 0,
        "min": "24"
      },
      {
        "playerId": 1057395754,
        "name": "Tyrese Proctor",
        "bucket": "PG",
        "isStarter": false,
        "pts": 3,
        "reb": 2,
        "ast": 1,
        "fg3m": 1,
        "stl": 1,
        "blk": 0,
        "min": "10"
      },
      {
        "playerId": 1028267470,
        "name": "Luke Travers",
        "bucket": "SF",
        "isStarter": false,
        "pts": 2,
        "reb": 1,
        "ast": 0,
        "fg3m": 0,
        "stl": 0,
        "blk": 0,
        "min": "07"
      },
      {
        "playerId": 1028028993,
        "name": "Jaylon Tyson",
        "bucket": "SF",
        "isStarter": false,
        "pts": 3,
        "reb": 2,
        "ast": 1,
        "fg3m": 0,
        "stl": 0,
        "blk": 0,
        "min": "28"
      },
      {
        "playerId": 666940,
        "name": "Dean Wade",
        "bucket": "SF",
        "isStarter": false,
        "pts": 5,
        "reb": 6,
        "ast": 2,
        "fg3m": 1,
        "stl": 2,
        "blk": 0,
        "min": "20"
      },
      {
        "playerId": 27,
        "name": "Lonzo Ball",
        "bucket": "PG",
        "isStarter": false,
        "pts": 0,
        "reb": 0,
        "ast": 0,
        "fg3m": 0,
        "stl": 0,
        "blk": 0,
        "min": "00"
      },
      {
        "playerId": 666581,
        "name": "Darius Garland",
        "bucket": "PG",
        "isStarter": false,
        "pts": 0,
        "reb": 0,
        "ast": 0,
        "fg3m": 0,
        "stl": 0,
        "blk": 0,
        "min": "00"
      },
      {
        "playerId": 666908,
        "name": "Max Strus",
        "bucket": "SF",
        "isStarter": false,
        "pts": 0,
        "reb": 0,
        "ast": 0,
        "fg3m": 0,
        "stl": 0,
        "blk": 0,
        "min": "00"
      },
      {
        "playerId": 1042560902,
        "name": "Nae'Qwan Tomlin",
        "bucket": "PF",
        "isStarter": false,
        "pts": 0,
        "reb": 0,
        "ast": 0,
        "fg3m": 0,
        "stl": 0,
        "blk": 0,
        "min": "00"
      },
      {
        "playerId": 0,
        "name": "De X Andre Hunter",
        "bucket": "SF",
        "isStarter": true,
        "pts": 0,
        "reb": 0,
        "ast": 0,
        "fg3m": 0,
        "stl": 0,
        "blk": 0,
        "min": "0:00"
      },
      {
        "playerId": 0,
        "name": "Nae X Qwan Tomlin",
        "bucket": "PF",
        "isStarter": false,
        "pts": 0,
        "reb": 0,
        "ast": 0,
        "fg3m": 0,
        "stl": 0,
        "blk": 0,
        "min": "0:00"
      }
    ],
    "source": "bdl+espn"
  },
  {
    "gameId": "18446878",
    "date": "2025-10-29",
    "opponent": "ORL",
    "team": "DET",
    "season": "2025-26",
    "buckets": {
      "PG": 11,
      "SG": 22,
      "SF": 37,
      "PF": 28,
      "C": 18
    },
    "players": [
      {
        "playerId": 17896026,
        "name": "Franz Wagner",
        "bucket": "SF",
        "isStarter": true,
        "pts": 22,
        "reb": 7,
        "ast": 2,
        "fg3m": 3,
        "stl": 0,
        "blk": 1,
        "min": "33"
      },
      {
        "playerId": 38017683,
        "name": "Paolo Banchero",
        "bucket": "PF",
        "isStarter": true,
        "pts": 24,
        "reb": 11,
        "ast": 7,
        "fg3m": 0,
        "stl": 1,
        "blk": 1,
        "min": "34"
      },
      {
        "playerId": 85,
        "name": "Wendell Carter Jr.",
        "bucket": "C",
        "isStarter": true,
        "pts": 8,
        "reb": 2,
        "ast": 1,
        "fg3m": 2,
        "stl": 0,
        "blk": 0,
        "min": "15"
      },
      {
        "playerId": 3547287,
        "name": "Desmond Bane",
        "bucket": "SG",
        "isStarter": true,
        "pts": 12,
        "reb": 5,
        "ast": 2,
        "fg3m": 1,
        "stl": 0,
        "blk": 0,
        "min": "31"
      },
      {
        "playerId": 17896073,
        "name": "Jalen Suggs",
        "bucket": "PG",
        "isStarter": true,
        "pts": 8,
        "reb": 2,
        "ast": 5,
        "fg3m": 1,
        "stl": 2,
        "blk": 1,
        "min": "21"
      },
      {
        "playerId": 666442,
        "name": "Goga Bitadze",
        "bucket": "C",
        "isStarter": false,
        "pts": 10,
        "reb": 6,
        "ast": 2,
        "fg3m": 0,
        "stl": 0,
        "blk": 1,
        "min": "26"
      },
      {
        "playerId": 56677827,
        "name": "Anthony Black",
        "bucket": "SG",
        "isStarter": false,
        "pts": 10,
        "reb": 4,
        "ast": 1,
        "fg3m": 1,
        "stl": 1,
        "blk": 0,
        "min": "24"
      },
      {
        "playerId": 1028025497,
        "name": "Tristan Da Silva",
        "bucket": "SF",
        "isStarter": false,
        "pts": 15,
        "reb": 3,
        "ast": 0,
        "fg3m": 3,
        "stl": 0,
        "blk": 0,
        "min": "21"
      },
      {
        "playerId": 56677839,
        "name": "Jett Howard",
        "bucket": "SF",
        "isStarter": false,
        "pts": 0,
        "reb": 1,
        "ast": 0,
        "fg3m": 0,
        "stl": 0,
        "blk": 0,
        "min": "04"
      },
      {
        "playerId": 229,
        "name": "Jonathan Isaac",
        "bucket": "PF",
        "isStarter": false,
        "pts": 0,
        "reb": 0,
        "ast": 0,
        "fg3m": 0,
        "stl": 0,
        "blk": 1,
        "min": "06"
      },
      {
        "playerId": 249,
        "name": "Tyus Jones",
        "bucket": "PG",
        "isStarter": false,
        "pts": 3,
        "reb": 0,
        "ast": 1,
        "fg3m": 1,
        "stl": 0,
        "blk": 0,
        "min": "09"
      },
      {
        "playerId": 1057385481,
        "name": "Noah Penda",
        "bucket": "PF",
        "isStarter": false,
        "pts": 4,
        "reb": 2,
        "ast": 0,
        "fg3m": 0,
        "stl": 0,
        "blk": 0,
        "min": "12"
      },
      {
        "playerId": 1057279571,
        "name": "Jase Richardson",
        "bucket": "SG",
        "isStarter": false,
        "pts": 0,
        "reb": 0,
        "ast": 1,
        "fg3m": 0,
        "stl": 0,
        "blk": 0,
        "min": "04"
      },
      {
        "playerId": 38017734,
        "name": "Jamal Cain",
        "bucket": "PF",
        "isStarter": false,
        "pts": 0,
        "reb": 0,
        "ast": 0,
        "fg3m": 0,
        "stl": 0,
        "blk": 0,
        "min": "00"
      },
      {
        "playerId": 56677738,
        "name": "Colin Castleton",
        "bucket": "C",
        "isStarter": false,
        "pts": 0,
        "reb": 0,
        "ast": 0,
        "fg3m": 0,
        "stl": 0,
        "blk": 0,
        "min": "00"
      },
      {
        "playerId": 39398582,
        "name": "Orlando Robinson",
        "bucket": "C",
        "isStarter": false,
        "pts": 0,
        "reb": 0,
        "ast": 0,
        "fg3m": 0,
        "stl": 0,
        "blk": 0,
        "min": "00"
      },
      {
        "playerId": 462,
        "name": "Moritz Wagner",
        "bucket": "SF",
        "isStarter": false,
        "pts": 0,
        "reb": 0,
        "ast": 0,
        "fg3m": 0,
        "stl": 0,
        "blk": 0,
        "min": "00"
      }
    ],
    "source": "bdl+espn"
  }
]