{
  "generatedAt": "2026-07-21T12:22:43.275Z",
  "source": "open-meteo.com",
  "gameSource": "props-list-fallback",
  "games": [
    {
      "gameId": "0f997b03220985cb6d6e3da6fd0c7beb",
      "homeTeam": "Adelaide Crows",
      "awayTeam": "Collingwood Magpies",
      "commenceTime": "2026-07-23T09:30:00Z",
      "weather": {
        "temperatureC": 10.3,
        "precipitationMm": 0,
        "windKmh": 13.7
      }
    },
    {
      "gameId": "150ebfd13cca1c188aa9e905fa4f1562",
      "homeTeam": "Melbourne Demons",
      "awayTeam": "Geelong Cats",
      "commenceTime": "2026-07-24T09:40:00Z",
      "weather": {
        "temperatureC": 11.1,
        "precipitationMm": 0,
        "windKmh": 12.3
      }
    },
    {
      "gameId": "cc105025545926548add36d1fb70581c",
      "homeTeam": "Fremantle Dockers",
      "awayTeam": "West Coast Eagles",
      "commenceTime": "2026-07-24T10:10:00Z",
      "weather": {
        "temperatureC": 13.8,
        "precipitationMm": 0,
        "windKmh": 6.4
      }
    },
    {
      "gameId": "cbebfb3093277cace962aab4f8a48d12",
      "homeTeam": "Carlton Blues",
      "awayTeam": "Gold Coast Suns",
      "commenceTime": "2026-07-25T03:05:56Z",
      "weather": {
        "temperatureC": 14.6,
        "precipitationMm": 0,
        "windKmh": 13.8
      }
    },
    {
      "gameId": "0e2c077cde7e1f2b878ddbadc57580d4",
      "homeTeam": "Hawthorn Hawks",
      "awayTeam": "Essendon Bombers",
      "commenceTime": "2026-07-25T06:15:34Z",
      "weather": {
        "temperatureC": 14.1,
        "precipitationMm": 0,
        "windKmh": 11.5
      }
    },
    {
      "gameId": "7b4827168998f2b7956467f28b96b9ef",
      "homeTeam": "GWS Giants",
      "awayTeam": "Sydney Swans",
      "commenceTime": "2026-07-25T06:35:15Z",
      "weather": {
        "temperatureC": 16.3,
        "precipitationMm": 0,
        "windKmh": 4.2
      }
    },
    {
      "gameId": "bfbe786d7ee6f3a6fea2c55fd4499e06",
      "homeTeam": "Western Bulldogs",
      "awayTeam": "Richmond Tigers",
      "commenceTime": "2026-07-25T09:40:45Z",
      "weather": {
        "temperatureC": 11.9,
        "precipitationMm": 0,
        "windKmh": 12.2
      }
    },
    {
      "gameId": "7080c6f79a69fe588148e7817af9f51b",
      "homeTeam": "Brisbane Lions",
      "awayTeam": "Port Adelaide Power",
      "commenceTime": "2026-07-26T03:10:00Z",
      "weather": {
        "temperatureC": 19.6,
        "precipitationMm": 0,
        "windKmh": 4.5
      }
    },
    {
      "gameId": "9afd85bee9081e6185c8b19c55793a61",
      "homeTeam": "North Melbourne Kangaroos",
      "awayTeam": "St Kilda Saints",
      "commenceTime": "2026-07-26T05:15:00Z",
      "weather": {
        "temperatureC": 15.4,
        "precipitationMm": 0,
        "windKmh": 6.9
      }
    },
    {
      "gameId": "fe134697b363633dd1547d5dbbd0502e",
      "homeTeam": "Collingwood Magpies",
      "awayTeam": "Geelong Cats",
      "commenceTime": "2026-07-30T09:30:41Z",
      "weather": {
        "temperatureC": 10.4,
        "precipitationMm": 0.1,
        "windKmh": 11.6
      }
    },
    {
      "gameId": "583afbf3b20e1683ea65b002a550369c",
      "homeTeam": "Fremantle Dockers",
      "awayTeam": "Western Bulldogs",
      "commenceTime": "2026-07-31T10:10:34Z",
      "weather": {
        "temperatureC": 12.5,
        "precipitationMm": 0.1,
        "windKmh": 18.2
      }
    },
    {
      "gameId": "e00a38510a6f146226a2c76b258317f0",
      "homeTeam": "St Kilda Saints",
      "awayTeam": "Sydney Swans",
      "commenceTime": "2026-08-01T03:05:21Z",
      "weather": {
        "temperatureC": 10.1,
        "precipitationMm": 0,
        "windKmh": 2.3
      }
    },
    {
      "gameId": "630516e7ac46e0e0f8e74653c0eae5d2",
      "homeTeam": "Hawthorn Hawks",
      "awayTeam": "North Melbourne Kangaroos",
      "commenceTime": "2026-08-01T03:35:16Z",
      "weather": {
        "temperatureC": 10.1,
        "precipitationMm": 0,
        "windKmh": 2.3
      }
    },
    {
      "gameId": "189439ba595578a4eaa1265764e6db05",
      "homeTeam": "Port Adelaide Power",
      "awayTeam": "GWS Giants",
      "commenceTime": "2026-08-01T08:35:50Z",
      "weather": {
        "temperatureC": 11.9,
        "precipitationMm": 0,
        "windKmh": 5.1
      }
    },
    {
      "gameId": "fd1209e1c95a9ce85e4c38e650346559",
      "homeTeam": "Carlton Blues",
      "awayTeam": "Brisbane Lions",
      "commenceTime": "2026-08-01T09:40:21Z",
      "weather": {
        "temperatureC": 11.3,
        "precipitationMm": 0,
        "windKmh": 5.2
      }
    },
    {
      "gameId": "aa6702db8b16592cca6555c008569df4",
      "homeTeam": "Richmond Tigers",
      "awayTeam": "West Coast Eagles",
      "commenceTime": "2026-08-02T03:10:58Z",
      "weather": {
        "temperatureC": 10,
        "precipitationMm": 0,
        "windKmh": 1.5
      }
    },
    {
      "gameId": "ce6bb6cdb9e9ae2280b10ab5ed96b888",
      "homeTeam": "Gold Coast Suns",
      "awayTeam": "Melbourne Demons",
      "commenceTime": "2026-08-02T05:15:45Z",
      "weather": {
        "temperatureC": 18.5,
        "precipitationMm": 0,
        "windKmh": 20.1
      }
    },
    {
      "gameId": "29ec920bf80140fb234d01d33e7b434c",
      "homeTeam": "Essendon Bombers",
      "awayTeam": "Adelaide Crows",
      "commenceTime": "2026-08-02T06:40:19Z",
      "weather": {
        "temperatureC": 11.2,
        "precipitationMm": 0,
        "windKmh": 3.8
      }
    }
  ],
  "count": 18
}