{
  "version": "afl-disp-20260406-114600",
  "createdAt": "2026-04-06T11:46:00Z",
  "datasetPath": "/home/runner/work/stattrackr/stattrackr/data/afl-model/datasets/afl-disposals-train-20260406-114555.csv",
  "featureColumns": [
    "roll3_mean",
    "roll5_mean",
    "roll10_mean",
    "roll5_std",
    "roll10_std",
    "lag1",
    "games_history",
    "tog_roll5_mean",
    "cp_roll5_mean",
    "up_roll5_mean",
    "cl_roll5_mean",
    "i50_roll5_mean",
    "mg_roll5_mean",
    "rest_days",
    "rest_short_le5",
    "rest_normal_6_8",
    "rest_long_ge9",
    "post_bye_team",
    "is_true_home",
    "is_shared_home_away_venue",
    "is_interstate_travel",
    "venue_player_disp_last5",
    "venue_player_tog_last5",
    "selection_low_tog_rate_last5",
    "selection_tog_std_last5",
    "selection_games_since_low_tog",
    "opp_role_disp_index",
    "opp_role_disp_ppg",
    "team_ta_disposals",
    "opp_ta_disposals",
    "game_pace_disposals_avg",
    "opp_allow_disposals",
    "opp_allow_kicks",
    "opp_allow_handballs",
    "opp_allow_cp",
    "opp_allow_up",
    "opp_allow_clearances",
    "opp_allow_i50",
    "opp_allow_mg",
    "dfs_cba_pct",
    "dfs_kickins",
    "delta_disp_3v10",
    "delta_tog_3v10",
    "delta_cp_3v10",
    "delta_up_3v10",
    "delta_cl_3v10",
    "cba_momentum_proxy"
  ],
  "modelType": "hgb",
  "modelPicklePath": "models/afl-disp-20260406-114600.pkl",
  "residualStd": 4.903327329700795,
  "metrics": {
    "baseline": {
      "mae": 4.187150834593719,
      "rmse": 5.325261398367161
    },
    "ridge": {
      "mae": 3.862410265806302,
      "rmse": 4.962373997338832,
      "cv_mae": 3.9368443607058103,
      "cv_rmse": 5.031550132827781,
      "bestParams": {
        "alpha": 4.0
      }
    },
    "hgb": {
      "mae": 3.79550396293822,
      "rmse": 4.903327329700795,
      "cv_mae": 3.9612733594663787,
      "cv_rmse": 5.043683601317406,
      "bestParams": {
        "max_depth": 4,
        "learning_rate": 0.05,
        "max_iter": 220,
        "min_samples_leaf": 20
      }
    }
  },
  "featureImportance": [
    {
      "feature": "roll10_mean",
      "maeLift": 1.877022,
      "permutedMae": 5.506402
    },
    {
      "feature": "opp_role_disp_index",
      "maeLift": 0.090982,
      "permutedMae": 3.720361
    },
    {
      "feature": "roll5_mean",
      "maeLift": 0.08288,
      "permutedMae": 3.712259
    },
    {
      "feature": "dfs_kickins",
      "maeLift": 0.030253,
      "permutedMae": 3.659633
    },
    {
      "feature": "cl_roll5_mean",
      "maeLift": 0.027859,
      "permutedMae": 3.657238
    },
    {
      "feature": "selection_games_since_low_tog",
      "maeLift": 0.027637,
      "permutedMae": 3.657017
    },
    {
      "feature": "lag1",
      "maeLift": 0.02313,
      "permutedMae": 3.65251
    },
    {
      "feature": "selection_tog_std_last5",
      "maeLift": 0.020097,
      "permutedMae": 3.649476
    },
    {
      "feature": "rest_days",
      "maeLift": 0.018094,
      "permutedMae": 3.647474
    },
    {
      "feature": "roll10_std",
      "maeLift": 0.016763,
      "permutedMae": 3.646143
    },
    {
      "feature": "mg_roll5_mean",
      "maeLift": 0.016726,
      "permutedMae": 3.646105
    },
    {
      "feature": "delta_disp_3v10",
      "maeLift": 0.015764,
      "permutedMae": 3.645144
    },
    {
      "feature": "delta_tog_3v10",
      "maeLift": 0.011862,
      "permutedMae": 3.641242
    },
    {
      "feature": "delta_cl_3v10",
      "maeLift": 0.011355,
      "permutedMae": 3.640734
    },
    {
      "feature": "cp_roll5_mean",
      "maeLift": 0.009012,
      "permutedMae": 3.638391
    },
    {
      "feature": "venue_player_disp_last5",
      "maeLift": 0.008576,
      "permutedMae": 3.637956
    },
    {
      "feature": "is_true_home",
      "maeLift": 0.006221,
      "permutedMae": 3.6356
    },
    {
      "feature": "opp_allow_handballs",
      "maeLift": 0.00619,
      "permutedMae": 3.635569
    },
    {
      "feature": "i50_roll5_mean",
      "maeLift": 0.00564,
      "permutedMae": 3.635019
    },
    {
      "feature": "opp_allow_disposals",
      "maeLift": 0.005354,
      "permutedMae": 3.634733
    },
    {
      "feature": "roll3_mean",
      "maeLift": 0.004804,
      "permutedMae": 3.634183
    },
    {
      "feature": "game_pace_disposals_avg",
      "maeLift": 0.003436,
      "permutedMae": 3.632815
    },
    {
      "feature": "games_history",
      "maeLift": 0.003097,
      "permutedMae": 3.632476
    },
    {
      "feature": "venue_player_tog_last5",
      "maeLift": 0.003081,
      "permutedMae": 3.632461
    },
    {
      "feature": "opp_role_disp_ppg",
      "maeLift": 0.002379,
      "permutedMae": 3.631758
    },
    {
      "feature": "selection_low_tog_rate_last5",
      "maeLift": 0.00225,
      "permutedMae": 3.631629
    },
    {
      "feature": "dfs_cba_pct",
      "maeLift": 0.002249,
      "permutedMae": 3.631628
    },
    {
      "feature": "roll5_std",
      "maeLift": 0.002225,
      "permutedMae": 3.631604
    },
    {
      "feature": "opp_allow_i50",
      "maeLift": 0.001892,
      "permutedMae": 3.631272
    },
    {
      "feature": "delta_up_3v10",
      "maeLift": 0.001479,
      "permutedMae": 3.630859
    },
    {
      "feature": "rest_normal_6_8",
      "maeLift": 0.001374,
      "permutedMae": 3.630754
    },
    {
      "feature": "up_roll5_mean",
      "maeLift": 0.001067,
      "permutedMae": 3.630447
    },
    {
      "feature": "team_ta_disposals",
      "maeLift": 0.000681,
      "permutedMae": 3.630061
    },
    {
      "feature": "opp_allow_clearances",
      "maeLift": 0.000537,
      "permutedMae": 3.629917
    },
    {
      "feature": "is_shared_home_away_venue",
      "maeLift": 0.000175,
      "permutedMae": 3.629555
    },
    {
      "feature": "opp_allow_mg",
      "maeLift": 1.4e-05,
      "permutedMae": 3.629393
    },
    {
      "feature": "rest_short_le5",
      "maeLift": 0.0,
      "permutedMae": 3.629379
    },
    {
      "feature": "rest_long_ge9",
      "maeLift": 0.0,
      "permutedMae": 3.629379
    },
    {
      "feature": "post_bye_team",
      "maeLift": 0.0,
      "permutedMae": 3.629379
    },
    {
      "feature": "opp_allow_up",
      "maeLift": 0.0,
      "permutedMae": 3.629379
    },
    {
      "feature": "opp_allow_kicks",
      "maeLift": -0.000389,
      "permutedMae": 3.628991
    },
    {
      "feature": "opp_ta_disposals",
      "maeLift": -0.000662,
      "permutedMae": 3.628717
    },
    {
      "feature": "is_interstate_travel",
      "maeLift": -0.00076,
      "permutedMae": 3.628619
    },
    {
      "feature": "opp_allow_cp",
      "maeLift": -0.001474,
      "permutedMae": 3.627906
    },
    {
      "feature": "tog_roll5_mean",
      "maeLift": -0.002089,
      "permutedMae": 3.62729
    },
    {
      "feature": "delta_cp_3v10",
      "maeLift": -0.004826,
      "permutedMae": 3.624553
    },
    {
      "feature": "cba_momentum_proxy",
      "maeLift": -0.011472,
      "permutedMae": 3.617908
    }
  ],
  "dropCandidates": [],
  "validationRows": 2573,
  "trainRows": 10289,
  "importanceRowsUsed": 1200,
  "calibrationPath": "models/afl-disp-20260406-114600.calibration.json",
  "calibrationMethod": "identity",
  "calibrationSampleCount": 0
}