{
  "savedAt": "2026-04-08T19:06:03Z",
  "games": [
    {
      "season": 2024,
      "game_number": 1,
      "opponent": "Power",
      "round": "R24",
      "date": "2024-08-24",
      "result": "Loss 67-87",
      "guernsey": null,
      "kicks": 10,
      "marks": 7,
      "handballs": 23,
      "disposals": 33,
      "goals": 0,
      "behinds": 0,
      "hitouts": 0,
      "tackles": 7,
      "rebounds": 0,
      "inside_50s": 5,
      "clearances": 5,
      "intercepts": 5,
      "tackles_inside_50": 1,
      "score_involvements": 4,
      "meters_gained": 354,
      "clangers": 5,
      "free_kicks_for": 2,
      "free_kicks_against": 1,
      "brownlow_votes": 0,
      "contested_possessions": 15,
      "uncontested_possessions": 18,
      "contested_marks": 0,
      "marks_inside_50": 0,
      "one_percenters": 1,
      "bounces": 1,
      "goal_assists": 0,
      "fantasy_points": 124,
      "percent_played": 87,
      "effective_disposals": 25,
      "disposal_efficiency": 76,
      "match_url": null
    },
    {
      "season": 2024,
      "game_number": 2,
      "opponent": "Giants",
      "round": "R23",
      "date": "2024-08-16",
      "result": "Loss 92-101",
      "guernsey": null,
      "kicks": 14,
      "marks": 3,
      "handballs": 27,
      "disposals": 41,
      "goals": 0,
      "behinds": 0,
      "hitouts": 0,
      "tackles": 4,
      "rebounds": 2,
      "inside_50s": 4,
      "clearances": 9,
      "intercepts": 7,
      "tackles_inside_50": 1,
      "score_involvements": 7,
      "meters_gained": 487,
      "clangers": 3,
      "free_kicks_for": 2,
      "free_kicks_against": 0,
      "brownlow_votes": 0,
      "contested_possessions": 21,
      "uncontested_possessions": 21,
      "contested_marks": 0,
      "marks_inside_50": 0,
      "one_percenters": 4,
      "bounces": 0,
      "goal_assists": 0,
      "fantasy_points": 123,
      "percent_played": 84,
      "effective_disposals": 26,
      "disposal_efficiency": 64,
      "match_url": null
    },
    {
      "season": 2024,
      "game_number": 3,
      "opponent": "Cats",
      "round": "R22",
      "date": "2024-08-09",
      "result": "Loss 62-73",
      "guernsey": null,
      "kicks": 10,
      "marks": 6,
      "handballs": 10,
      "disposals": 20,
      "goals": 0,
      "behinds": 1,
      "hitouts": 0,
      "tackles": 3,
      "rebounds": 0,
      "inside_50s": 2,
      "clearances": 4,
      "intercepts": 1,
      "tackles_inside_50": 1,
      "score_involvements": 7,
      "meters_gained": 280,
      "clangers": 2,
      "free_kicks_for": 3,
      "free_kicks_against": 1,
      "brownlow_votes": 0,
      "contested_possessions": 6,
      "uncontested_possessions": 14,
      "contested_marks": 0,
      "marks_inside_50": 0,
      "one_percenters": 2,
      "bounces": 0,
      "goal_assists": 0,
      "fantasy_points": 81,
      "percent_played": 85,
      "effective_disposals": 15,
      "disposal_efficiency": 75,
      "match_url": null
    },
    {
      "season": 2024,
      "game_number": 4,
      "opponent": "Bombers",
      "round": "R21",
      "date": "2024-08-03",
      "result": "Loss 89-90",
      "guernsey": null,
      "kicks": 12,
      "marks": 6,
      "handballs": 21,
      "disposals": 33,
      "goals": 0,
      "behinds": 0,
      "hitouts": 0,
      "tackles": 5,
      "rebounds": 5,
      "inside_50s": 3,
      "clearances": 8,
      "intercepts": 4,
      "tackles_inside_50": 1,
      "score_involvements": 5,
      "meters_gained": 319,
      "clangers": 4,
      "free_kicks_for": 2,
      "free_kicks_against": 3,
      "brownlow_votes": 0,
      "contested_possessions": 16,
      "uncontested_possessions": 20,
      "contested_marks": 0,
      "marks_inside_50": 0,
      "one_percenters": 2,
      "bounces": 1,
      "goal_assists": 0,
      "fantasy_points": 109,
      "percent_played": 80,
      "effective_disposals": 30,
      "disposal_efficiency": 91,
      "match_url": null
    },
    {
      "season": 2024,
      "game_number": 5,
      "opponent": "Eagles",
      "round": "R20",
      "date": "2024-07-26",
      "result": "Win 110-75",
      "guernsey": null,
      "kicks": 16,
      "marks": 2,
      "handballs": 20,
      "disposals": 36,
      "goals": 1,
      "behinds": 1,
      "hitouts": 0,
      "tackles": 7,
      "rebounds": 1,
      "inside_50s": 7,
      "clearances": 5,
      "intercepts": 3,
      "tackles_inside_50": 0,
      "score_involvements": 14,
      "meters_gained": 532,
      "clangers": 6,
      "free_kicks_for": 1,
      "free_kicks_against": 5,
      "brownlow_votes": 0,
      "contested_possessions": 10,
      "uncontested_possessions": 25,
      "contested_marks": 0,
      "marks_inside_50": 0,
      "one_percenters": 1,
      "bounces": 3,
      "goal_assists": 1,
      "fantasy_points": 115,
      "percent_played": 85,
      "effective_disposals": 25,
      "disposal_efficiency": 70,
      "match_url": null
    },
    {
      "season": 2024,
      "game_number": 6,
      "opponent": "Demons",
      "round": "R19",
      "date": "2024-07-20",
      "result": "Win 116-66",
      "guernsey": null,
      "kicks": 17,
      "marks": 3,
      "handballs": 24,
      "disposals": 41,
      "goals": 0,
      "behinds": 0,
      "hitouts": 0,
      "tackles": 3,
      "rebounds": 2,
      "inside_50s": 6,
      "clearances": 4,
      "intercepts": 6,
      "tackles_inside_50": 0,
      "score_involvements": 7,
      "meters_gained": 551,
      "clangers": 7,
      "free_kicks_for": 3,
      "free_kicks_against": 1,
      "brownlow_votes": 0,
      "contested_possessions": 13,
      "uncontested_possessions": 27,
      "contested_marks": 0,
      "marks_inside_50": 1,
      "one_percenters": 5,
      "bounces": 1,
      "goal_assists": 1,
      "fantasy_points": 120,
      "percent_played": 81,
      "effective_disposals": 31,
      "disposal_efficiency": 76,
      "match_url": null
    },
    {
      "season": 2024,
      "game_number": 7,
      "opponent": "Hawks",
      "round": "R18",
      "date": "2024-07-12",
      "result": "Loss 74-87",
      "guernsey": null,
      "kicks": 8,
      "marks": 3,
      "handballs": 15,
      "disposals": 23,
      "goals": 1,
      "behinds": 0,
      "hitouts": 0,
      "tackles": 6,
      "rebounds": 0,
      "inside_50s": 3,
      "clearances": 2,
      "intercepts": 2,
      "tackles_inside_50": 1,
      "score_involvements": 5,
      "meters_gained": 234,
      "clangers": 4,
      "free_kicks_for": 0,
      "free_kicks_against": 3,
      "brownlow_votes": 0,
      "contested_possessions": 11,
      "uncontested_possessions": 12,
      "contested_marks": 0,
      "marks_inside_50": 1,
      "one_percenters": 1,
      "bounces": 0,
      "goal_assists": 0,
      "fantasy_points": 84,
      "percent_played": 79,
      "effective_disposals": 16,
      "disposal_efficiency": 70,
      "match_url": null
    },
    {
      "season": 2024,
      "game_number": 8,
      "opponent": "Tigers",
      "round": "R17",
      "date": "2024-07-05",
      "result": "Win 105-54",
      "guernsey": null,
      "kicks": 20,
      "marks": 8,
      "handballs": 15,
      "disposals": 35,
      "goals": 1,
      "behinds": 1,
      "hitouts": 0,
      "tackles": 8,
      "rebounds": 2,
      "inside_50s": 5,
      "clearances": 6,
      "intercepts": 0,
      "tackles_inside_50": 0,
      "score_involvements": 10,
      "meters_gained": 415,
      "clangers": 8,
      "free_kicks_for": 2,
      "free_kicks_against": 3,
      "brownlow_votes": 0,
      "contested_possessions": 11,
      "uncontested_possessions": 25,
      "contested_marks": 0,
      "marks_inside_50": 2,
      "one_percenters": 1,
      "bounces": 0,
      "goal_assists": 1,
      "fantasy_points": 146,
      "percent_played": 87,
      "effective_disposals": 23,
      "disposal_efficiency": 66,
      "match_url": null
    },
    {
      "season": 2024,
      "game_number": 9,
      "opponent": "Swans",
      "round": "R16",
      "date": "2024-06-28",
      "result": "Win 99-98",
      "guernsey": null,
      "kicks": 14,
      "marks": 4,
      "handballs": 10,
      "disposals": 24,
      "goals": 0,
      "behinds": 0,
      "hitouts": 0,
      "tackles": 3,
      "rebounds": 1,
      "inside_50s": 4,
      "clearances": 5,
      "intercepts": 0,
      "tackles_inside_50": 0,
      "score_involvements": 9,
      "meters_gained": 414,
      "clangers": 6,
      "free_kicks_for": 0,
      "free_kicks_against": 2,
      "brownlow_votes": 0,
      "contested_possessions": 9,
      "uncontested_possessions": 15,
      "contested_marks": 0,
      "marks_inside_50": 1,
      "one_percenters": 0,
      "bounces": 0,
      "goal_assists": 0,
      "fantasy_points": 80,
      "percent_played": 83,
      "effective_disposals": 16,
      "disposal_efficiency": 67,
      "match_url": null
    },
    {
      "season": 2024,
      "game_number": 10,
      "opponent": "Suns",
      "round": "R15",
      "date": "2024-06-22",
      "result": "Win 85-65",
      "guernsey": null,
      "kicks": 16,
      "marks": 5,
      "handballs": 16,
      "disposals": 32,
      "goals": 1,
      "behinds": 1,
      "hitouts": 0,
      "tackles": 8,
      "rebounds": 1,
      "inside_50s": 2,
      "clearances": 7,
      "intercepts": 5,
      "tackles_inside_50": 1,
      "score_involvements": 10,
      "meters_gained": 390,
      "clangers": 4,
      "free_kicks_for": 2,
      "free_kicks_against": 0,
      "brownlow_votes": 0,
      "contested_possessions": 14,
      "uncontested_possessions": 19,
      "contested_marks": 0,
      "marks_inside_50": 1,
      "one_percenters": 1,
      "bounces": 0,
      "goal_assists": 1,
      "fantasy_points": 136,
      "percent_played": 85,
      "effective_disposals": 22,
      "disposal_efficiency": 69,
      "match_url": null
    },
    {
      "season": 2024,
      "game_number": 11,
      "opponent": "Bulldogs",
      "round": "R14",
      "date": "2024-06-14",
      "result": "Loss 82-149",
      "guernsey": null,
      "kicks": 9,
      "marks": 0,
      "handballs": 12,
      "disposals": 21,
      "goals": 0,
      "behinds": 0,
      "hitouts": 0,
      "tackles": 4,
      "rebounds": 3,
      "inside_50s": 1,
      "clearances": 4,
      "intercepts": 0,
      "tackles_inside_50": 0,
      "score_involvements": 8,
      "meters_gained": 228,
      "clangers": 3,
      "free_kicks_for": 0,
      "free_kicks_against": 0,
      "brownlow_votes": 0,
      "contested_possessions": 11,
      "uncontested_possessions": 8,
      "contested_marks": 0,
      "marks_inside_50": 0,
      "one_percenters": 0,
      "bounces": 0,
      "goal_assists": 1,
      "fantasy_points": 67,
      "percent_played": 89,
      "effective_disposals": 9,
      "disposal_efficiency": 43,
      "match_url": null
    },
    {
      "season": 2024,
      "game_number": 12,
      "opponent": "Demons",
      "round": "R12",
      "date": "2024-06-01",
      "result": "Win 141-49",
      "guernsey": null,
      "kicks": 16,
      "marks": 4,
      "handballs": 9,
      "disposals": 25,
      "goals": 0,
      "behinds": 1,
      "hitouts": 0,
      "tackles": 4,
      "rebounds": 1,
      "inside_50s": 4,
      "clearances": 8,
      "intercepts": 1,
      "tackles_inside_50": 0,
      "score_involvements": 6,
      "meters_gained": 442,
      "clangers": 3,
      "free_kicks_for": 1,
      "free_kicks_against": 0,
      "brownlow_votes": 0,
      "contested_possessions": 10,
      "uncontested_possessions": 14,
      "contested_marks": 1,
      "marks_inside_50": 0,
      "one_percenters": 1,
      "bounces": 1,
      "goal_assists": 0,
      "fantasy_points": 96,
      "percent_played": 83,
      "effective_disposals": 16,
      "disposal_efficiency": 64,
      "match_url": null
    },
    {
      "season": 2024,
      "game_number": 13,
      "opponent": "Magpies",
      "round": "R11",
      "date": "2024-05-23",
      "result": "Draw 75-75",
      "guernsey": null,
      "kicks": 15,
      "marks": 5,
      "handballs": 16,
      "disposals": 31,
      "goals": 1,
      "behinds": 2,
      "hitouts": 0,
      "tackles": 2,
      "rebounds": 1,
      "inside_50s": 4,
      "clearances": 3,
      "intercepts": 2,
      "tackles_inside_50": 0,
      "score_involvements": 7,
      "meters_gained": 284,
      "clangers": 3,
      "free_kicks_for": 0,
      "free_kicks_against": 1,
      "brownlow_votes": 0,
      "contested_possessions": 9,
      "uncontested_possessions": 17,
      "contested_marks": 0,
      "marks_inside_50": 1,
      "one_percenters": 1,
      "bounces": 0,
      "goal_assists": 1,
      "fantasy_points": 105,
      "percent_played": 86,
      "effective_disposals": 18,
      "disposal_efficiency": 59,
      "match_url": null
    },
    {
      "season": 2024,
      "game_number": 14,
      "opponent": "Saints",
      "round": "R10",
      "date": "2024-05-17",
      "result": "Win 72-55",
      "guernsey": null,
      "kicks": 12,
      "marks": 2,
      "handballs": 14,
      "disposals": 26,
      "goals": 0,
      "behinds": 0,
      "hitouts": 0,
      "tackles": 6,
      "rebounds": 1,
      "inside_50s": 5,
      "clearances": 8,
      "intercepts": 1,
      "tackles_inside_50": 0,
      "score_involvements": 8,
      "meters_gained": 337,
      "clangers": 1,
      "free_kicks_for": 3,
      "free_kicks_against": 1,
      "brownlow_votes": 0,
      "contested_possessions": 11,
      "uncontested_possessions": 14,
      "contested_marks": 0,
      "marks_inside_50": 0,
      "one_percenters": 0,
      "bounces": 1,
      "goal_assists": 0,
      "fantasy_points": 94,
      "percent_played": 77,
      "effective_disposals": 23,
      "disposal_efficiency": 89,
      "match_url": null
    },
    {
      "season": 2024,
      "game_number": 15,
      "opponent": "Swans",
      "round": "R9",
      "date": "2024-05-09",
      "result": "Loss 39-87",
      "guernsey": null,
      "kicks": 11,
      "marks": 5,
      "handballs": 14,
      "disposals": 25,
      "goals": 0,
      "behinds": 1,
      "hitouts": 0,
      "tackles": 6,
      "rebounds": 3,
      "inside_50s": 1,
      "clearances": 5,
      "intercepts": 2,
      "tackles_inside_50": 1,
      "score_involvements": 7,
      "meters_gained": 293,
      "clangers": 6,
      "free_kicks_for": 3,
      "free_kicks_against": 2,
      "brownlow_votes": 0,
      "contested_possessions": 9,
      "uncontested_possessions": 16,
      "contested_marks": 0,
      "marks_inside_50": 0,
      "one_percenters": 0,
      "bounces": 0,
      "goal_assists": 0,
      "fantasy_points": 98,
      "percent_played": 79,
      "effective_disposals": 18,
      "disposal_efficiency": 72,
      "match_url": null
    },
    {
      "season": 2024,
      "game_number": 16,
      "opponent": "Tigers",
      "round": "R8",
      "date": "2024-05-04",
      "result": "Win 103-49",
      "guernsey": null,
      "kicks": 16,
      "marks": 6,
      "handballs": 15,
      "disposals": 31,
      "goals": 0,
      "behinds": 1,
      "hitouts": 0,
      "tackles": 7,
      "rebounds": 0,
      "inside_50s": 6,
      "clearances": 5,
      "intercepts": 2,
      "tackles_inside_50": 1,
      "score_involvements": 9,
      "meters_gained": 393,
      "clangers": 2,
      "free_kicks_for": 0,
      "free_kicks_against": 0,
      "brownlow_votes": 0,
      "contested_possessions": 7,
      "uncontested_possessions": 23,
      "contested_marks": 0,
      "marks_inside_50": 1,
      "one_percenters": 0,
      "bounces": 0,
      "goal_assists": 0,
      "fantasy_points": 125,
      "percent_played": 82,
      "effective_disposals": 20,
      "disposal_efficiency": 65,
      "match_url": null
    },
    {
      "season": 2024,
      "game_number": 17,
      "opponent": "Bulldogs",
      "round": "R7",
      "date": "2024-04-26",
      "result": "Win 95-71",
      "guernsey": null,
      "kicks": 10,
      "marks": 4,
      "handballs": 20,
      "disposals": 30,
      "goals": 0,
      "behinds": 2,
      "hitouts": 0,
      "tackles": 2,
      "rebounds": 1,
      "inside_50s": 4,
      "clearances": 7,
      "intercepts": 1,
      "tackles_inside_50": 1,
      "score_involvements": 11,
      "meters_gained": 293,
      "clangers": 3,
      "free_kicks_for": 1,
      "free_kicks_against": 2,
      "brownlow_votes": 0,
      "contested_possessions": 10,
      "uncontested_possessions": 22,
      "contested_marks": 0,
      "marks_inside_50": 1,
      "one_percenters": 2,
      "bounces": 0,
      "goal_assists": 0,
      "fantasy_points": 87,
      "percent_played": 86,
      "effective_disposals": 25,
      "disposal_efficiency": 84,
      "match_url": null
    },
    {
      "season": 2024,
      "game_number": 18,
      "opponent": "Eagles",
      "round": "R6",
      "date": "2024-04-19",
      "result": "Loss 68-105",
      "guernsey": null,
      "kicks": 10,
      "marks": 4,
      "handballs": 17,
      "disposals": 27,
      "goals": 0,
      "behinds": 0,
      "hitouts": 0,
      "tackles": 5,
      "rebounds": 3,
      "inside_50s": 1,
      "clearances": 3,
      "intercepts": 0,
      "tackles_inside_50": 0,
      "score_involvements": 5,
      "meters_gained": 253,
      "clangers": 6,
      "free_kicks_for": 0,
      "free_kicks_against": 1,
      "brownlow_votes": 0,
      "contested_possessions": 10,
      "uncontested_possessions": 14,
      "contested_marks": 0,
      "marks_inside_50": 0,
      "one_percenters": 1,
      "bounces": 0,
      "goal_assists": 0,
      "fantasy_points": 93,
      "percent_played": 90,
      "effective_disposals": 20,
      "disposal_efficiency": 75,
      "match_url": null
    },
    {
      "season": 2024,
      "game_number": 19,
      "opponent": "Power",
      "round": "R5",
      "date": "2024-04-12",
      "result": "Loss 63-66",
      "guernsey": null,
      "kicks": 7,
      "marks": 0,
      "handballs": 11,
      "disposals": 18,
      "goals": 1,
      "behinds": 1,
      "hitouts": 0,
      "tackles": 6,
      "rebounds": 0,
      "inside_50s": 2,
      "clearances": 6,
      "intercepts": 4,
      "tackles_inside_50": 2,
      "score_involvements": 8,
      "meters_gained": 154,
      "clangers": 2,
      "free_kicks_for": 4,
      "free_kicks_against": 0,
      "brownlow_votes": 0,
      "contested_possessions": 14,
      "uncontested_possessions": 5,
      "contested_marks": 0,
      "marks_inside_50": 0,
      "one_percenters": 1,
      "bounces": 0,
      "goal_assists": 2,
      "fantasy_points": 78,
      "percent_played": 76,
      "effective_disposals": 13,
      "disposal_efficiency": 73,
      "match_url": null
    },
    {
      "season": 2024,
      "game_number": 20,
      "opponent": "Blues",
      "round": "R4",
      "date": "2024-04-05",
      "result": "Loss 63-73",
      "guernsey": null,
      "kicks": 21,
      "marks": 7,
      "handballs": 17,
      "disposals": 38,
      "goals": 0,
      "behinds": 0,
      "hitouts": 0,
      "tackles": 7,
      "rebounds": 3,
      "inside_50s": 6,
      "clearances": 4,
      "intercepts": 6,
      "tackles_inside_50": 0,
      "score_involvements": 3,
      "meters_gained": 553,
      "clangers": 7,
      "free_kicks_for": 2,
      "free_kicks_against": 0,
      "brownlow_votes": 0,
      "contested_possessions": 13,
      "uncontested_possessions": 24,
      "contested_marks": 0,
      "marks_inside_50": 0,
      "one_percenters": 0,
      "bounces": 0,
      "goal_assists": 0,
      "fantasy_points": 148,
      "percent_played": 85,
      "effective_disposals": 23,
      "disposal_efficiency": 61,
      "match_url": null
    },
    {
      "season": 2024,
      "game_number": 21,
      "opponent": "Crows",
      "round": "R3",
      "date": "2024-03-28",
      "result": "Win 69-34",
      "guernsey": null,
      "kicks": 9,
      "marks": 4,
      "handballs": 12,
      "disposals": 21,
      "goals": 0,
      "behinds": 0,
      "hitouts": 0,
      "tackles": 5,
      "rebounds": 2,
      "inside_50s": 2,
      "clearances": 1,
      "intercepts": 1,
      "tackles_inside_50": 0,
      "score_involvements": 4,
      "meters_gained": 312,
      "clangers": 1,
      "free_kicks_for": 1,
      "free_kicks_against": 0,
      "brownlow_votes": 0,
      "contested_possessions": 3,
      "uncontested_possessions": 16,
      "contested_marks": 0,
      "marks_inside_50": 0,
      "one_percenters": 3,
      "bounces": 1,
      "goal_assists": 0,
      "fantasy_points": 84,
      "percent_played": 80,
      "effective_disposals": 19,
      "disposal_efficiency": 91,
      "match_url": null
    },
    {
      "season": 2024,
      "game_number": 22,
      "opponent": "Kangaroos",
      "round": "R2",
      "date": "2024-03-22",
      "result": "Win 102-76",
      "guernsey": null,
      "kicks": 13,
      "marks": 3,
      "handballs": 14,
      "disposals": 27,
      "goals": 1,
      "behinds": 0,
      "hitouts": 0,
      "tackles": 3,
      "rebounds": 3,
      "inside_50s": 3,
      "clearances": 4,
      "intercepts": 5,
      "tackles_inside_50": 2,
      "score_involvements": 8,
      "meters_gained": 396,
      "clangers": 4,
      "free_kicks_for": 0,
      "free_kicks_against": 1,
      "brownlow_votes": 0,
      "contested_possessions": 10,
      "uncontested_possessions": 18,
      "contested_marks": 0,
      "marks_inside_50": 0,
      "one_percenters": 1,
      "bounces": 0,
      "goal_assists": 1,
      "fantasy_points": 91,
      "percent_played": 74,
      "effective_disposals": 21,
      "disposal_efficiency": 78,
      "match_url": null
    },
    {
      "season": 2024,
      "game_number": 23,
      "opponent": "Lions",
      "round": "R1",
      "date": "2024-03-16",
      "result": "Win 93-70",
      "guernsey": null,
      "kicks": 19,
      "marks": 8,
      "handballs": 13,
      "disposals": 32,
      "goals": 0,
      "behinds": 0,
      "hitouts": 0,
      "tackles": 5,
      "rebounds": 1,
      "inside_50s": 3,
      "clearances": 6,
      "intercepts": 1,
      "tackles_inside_50": 0,
      "score_involvements": 7,
      "meters_gained": 439,
      "clangers": 7,
      "free_kicks_for": 0,
      "free_kicks_against": 3,
      "brownlow_votes": 0,
      "contested_possessions": 11,
      "uncontested_possessions": 19,
      "contested_marks": 0,
      "marks_inside_50": 0,
      "one_percenters": 2,
      "bounces": 0,
      "goal_assists": 2,
      "fantasy_points": 118,
      "percent_played": 82,
      "effective_disposals": 21,
      "disposal_efficiency": 66,
      "match_url": null
    }
  ]
}